{"success":true,"data":[{"id":"cmko44unn00012cxg6yhb8icb","name":"Company Mapping Configuration (bacdbc1d-cf5b-4a87-a32a-5a677d17d2d2)","description":null,"scope":"COMPANY","companyId":"bacdbc1d-cf5b-4a87-a32a-5a677d17d2d2","company":{"id":"bacdbc1d-cf5b-4a87-a32a-5a677d17d2d2","name":"MSC","code":"MSC"},"documentFormatId":null,"documentFormat":null,"isActive":true,"version":1,"rulesCount":1,"createdAt":"2026-01-21T14:23:09.840Z","updatedAt":"2026-01-21T14:23:09.840Z"},{"id":"cmknua3lv00002cxgsf5m22t8","name":"Test Config","description":null,"scope":"GLOBAL","companyId":null,"company":null,"documentFormatId":null,"documentFormat":null,"isActive":true,"version":1,"rulesCount":15,"createdAt":"2026-01-21T09:47:18.592Z","updatedAt":"2026-01-21T09:47:18.592Z"}],"meta":{"pagination":{"page":1,"limit":20,"total":2,"totalPages":1}}}